{"_type":"export","__export_format":4,"__export_date":"2019-11-05T00:32:03.087Z","__export_source":"insomnia.desktop.app:v7.0.3","resources":[{"_id":"req_04d1d804fa7b4c7c88fe6ebf623a62e1","authentication":{},"body":{},"created":1572912558304,"description":"","headers":[],"isPrivate":false,"metaSortKey":-1570963642283.5,"method":"GET","modified":1572912727781,"name":"Show","parameters":[],"parentId":"fld_1389e038f7b7408785eb432eb41ed7d3","settingDisableRenderRequestBody":false,"settingEncodeUrl":true,"settingRebuildPath":true,"settingSendCookies":true,"settingStoreCookies":true,"url":"{{ base_url  }}/files/1572911857711.jpeg","_type":"request"},{"_id":"fld_1389e038f7b7408785eb432eb41ed7d3","created":1572911740630,"description":"","environment":{},"environmentPropertyOrder":null,"metaSortKey":-1572781682660,"modified":1572911747637,"name":"Files","parentId":"wrk_f49c733311f24289aaa06736ec4c7ef9","_type":"request_group"},{"_id":"wrk_f49c733311f24289aaa06736ec4c7ef9","created":1570960543802,"description":"","modified":1570960543802,"name":"Nomady Api","parentId":null,"_type":"workspace"},{"_id":"req_f7f26df92b064f0f80a6fea16faa5c62","authentication":{},"body":{"mimeType":"multipart/form-data","params":[{"fileName":"/home/gilmar/Pictures/landscape__1____forest_mountain_by_ncoll36_daxsdd5.jpg","id":"pair_91a8a17206524835994cef019966dffa","name":"file","type":"file","value":""},{"id":"pair_976477be94f543b382c54dd650c975c4","name":"","value":""}]},"created":1572911766826,"description":"","headers":[{"id":"pair_15bf16c2c7a7465aa9f98c8b37f053fa","name":"Content-Type","value":"multipart/form-data"}],"isPrivate":false,"metaSortKey":-1570963642233.5,"method":"POST","modified":1572913536067,"name":"Create","parameters":[],"parentId":"fld_1389e038f7b7408785eb432eb41ed7d3","settingDisableRenderRequestBody":false,"settingEncodeUrl":true,"settingRebuildPath":true,"settingSendCookies":true,"settingStoreCookies":true,"url":"{{ base_url  }}/files","_type":"request"},{"_id":"req_5b8e63fee46f468a8e95191f32f76039","authentication":{},"body":{"mimeType":"application/json","text":"{\n\t\"email\": \"gilmar.basilio@gmail.com\",\n\t\"redirect_url\": \"http://www.meusite.com.br/recuperar-senha/\"\n}"},"created":1572781691321,"description":"","headers":[{"id":"pair_15bf16c2c7a7465aa9f98c8b37f053fa","name":"Content-Type","value":"application/json"}],"isPrivate":false,"metaSortKey":-1570962865212,"method":"POST","modified":1572798181745,"name":"Create","parameters":[],"parentId":"fld_ca8257c8a02c4d808acafa0b2d49c615","settingDisableRenderRequestBody":false,"settingEncodeUrl":true,"settingRebuildPath":true,"settingSendCookies":true,"settingStoreCookies":true,"url":"{{ base_url  }}/passwords","_type":"request"},{"_id":"fld_ca8257c8a02c4d808acafa0b2d49c615","created":1572781682610,"description":"","environment":{},"environmentPropertyOrder":null,"metaSortKey":-1572781682610,"modified":1572781682610,"name":"ForgotPassword","parentId":"wrk_f49c733311f24289aaa06736ec4c7ef9","_type":"request_group"},{"_id":"req_1047ca85207141a696f53b1803861d30","authentication":{},"body":{"mimeType":"application/json","text":"{\n\t\"token\": \"34d811fc03990e108903\",\n\t\"password\": \"abc1234567\"\n}"},"created":1572908396037,"description":"","headers":[{"id":"pair_15bf16c2c7a7465aa9f98c8b37f053fa","name":"Content-Type","value":"application/json"}],"isPrivate":false,"metaSortKey":-1570962088190.5,"method":"PUT","modified":1572909313643,"name":"Update","parameters":[],"parentId":"fld_ca8257c8a02c4d808acafa0b2d49c615","settingDisableRenderRequestBody":false,"settingEncodeUrl":true,"settingRebuildPath":true,"settingSendCookies":true,"settingStoreCookies":true,"url":"{{ base_url  }}/passwords","_type":"request"},{"_id":"req_fd108c94f90641e39a8e189e276c398c","authentication":{"token":"{{ token  }}","type":"bearer"},"body":{},"created":1571793775184,"description":"","headers":[],"isPrivate":false,"metaSortKey":-1571134202790.5,"method":"GET","modified":1571796961131,"name":"Index","parameters":[],"parentId":"fld_e014a064cafb4acf8eb521368de4d6fe","settingDisableRenderRequestBody":false,"settingEncodeUrl":true,"settingRebuildPath":true,"settingSendCookies":true,"settingStoreCookies":true,"url":"{{ base_url  }}/projects","_type":"request"},{"_id":"fld_e014a064cafb4acf8eb521368de4d6fe","created":1571602725791,"description":"","environment":{},"environmentPropertyOrder":null,"metaSortKey":-1571602725791,"modified":1571602725791,"name":"Project","parentId":"wrk_f49c733311f24289aaa06736ec4c7ef9","_type":"request_group"},{"_id":"req_2a2e608d8cc94b1d93135c4d4f43b216","authentication":{"token":"{{ token  }}","type":"bearer"},"body":{"mimeType":"application/json","text":"{\n\t\"name\": \"App Android\",\n  \"customerId\": 4\n}\n\n"},"created":1571602732896,"description":"","headers":[{"id":"pair_a3e2297aa0fd42afb0b628b3d79b714f","name":"Content-Type","value":"application/json"}],"isPrivate":false,"metaSortKey":-1571134202740.5,"method":"POST","modified":1571794887681,"name":"Create","parameters":[],"parentId":"fld_e014a064cafb4acf8eb521368de4d6fe","settingDisableRenderRequestBody":false,"settingEncodeUrl":true,"settingRebuildPath":true,"settingSendCookies":true,"settingStoreCookies":true,"url":"{{ base_url  }}/projects","_type":"request"},{"_id":"req_0b39ae0a60de4fc8ac498b16e4624f54","authentication":{"token":"{{ token  }}","type":"bearer"},"body":{"mimeType":"application/json","text":"{\n\t\"name\": \"Casa nova 2\"\n}"},"created":1571907729487,"description":"","headers":[{"id":"pair_e4c2563d69be4cf99452a519204ef499","name":"Content-Type","value":"application/json"}],"isPrivate":false,"metaSortKey":-1571134202690.5,"method":"PUT","modified":1571907820931,"name":"Update","parameters":[],"parentId":"fld_e014a064cafb4acf8eb521368de4d6fe","settingDisableRenderRequestBody":false,"settingEncodeUrl":true,"settingRebuildPath":true,"settingSendCookies":true,"settingStoreCookies":true,"url":"{{ base_url  }}/projects/1","_type":"request"},{"_id":"req_275ef56c5fda4c5ca7d24fc17c69048e","authentication":{"token":"{{ token  }}","type":"bearer"},"body":{},"created":1571907944136,"description":"","headers":[],"isPrivate":false,"metaSortKey":-1571134202640.5,"method":"DELETE","modified":1571907973196,"name":"Delete","parameters":[],"parentId":"fld_e014a064cafb4acf8eb521368de4d6fe","settingDisableRenderRequestBody":true,"settingEncodeUrl":true,"settingRebuildPath":true,"settingSendCookies":true,"settingStoreCookies":true,"url":"{{ base_url  }}/projects/1","_type":"request"},{"_id":"req_22ec6d011090451299ca99085398929e","authentication":{"token":"{{ token  }}","type":"bearer"},"body":{"mimeType":"application/json","text":"{\n\t\"name\": \"Livia Teste\",\n  \"lastName\": \"Nishino\",\n  \"email\": \"livia4@gmail.com\",\n  \"phone\": \"61982816409\",\n\t\"active\": true\n}"},"created":1571483335175,"description":"","headers":[{"id":"pair_e4c2563d69be4cf99452a519204ef499","name":"Content-Type","value":"application/json"}],"isPrivate":false,"metaSortKey":-1571483335175,"method":"PUT","modified":1571529949884,"name":"Update","parameters":[],"parentId":"fld_7ffd25012c4243dfb1dc9621e5932cc6","settingDisableRenderRequestBody":false,"settingEncodeUrl":true,"settingRebuildPath":true,"settingSendCookies":true,"settingStoreCookies":true,"url":"{{ base_url  }}/customers/8","_type":"request"},{"_id":"fld_7ffd25012c4243dfb1dc9621e5932cc6","created":1571303972095,"description":"","environment":{},"environmentPropertyOrder":null,"metaSortKey":-1571303972095,"modified":1571303972095,"name":"Customer","parentId":"wrk_f49c733311f24289aaa06736ec4c7ef9","_type":"request_group"},{"_id":"req_a97f637135074a9682011832dea7d7cb","authentication":{"token":"{{ token  }}","type":"bearer"},"body":{},"created":1571531947023,"description":"","headers":[],"isPrivate":false,"metaSortKey":-1571464260162,"method":"DELETE","modified":1571531985824,"name":"Delete","parameters":[],"parentId":"fld_7ffd25012c4243dfb1dc9621e5932cc6","settingDisableRenderRequestBody":true,"settingEncodeUrl":true,"settingRebuildPath":true,"settingSendCookies":true,"settingStoreCookies":true,"url":"{{ base_url  }}/customers/8","_type":"request"},{"_id":"req_dbeec10a72c341589ddf39b981f826c5","authentication":{"token":"{{ token  }}","type":"bearer"},"body":{},"created":1571445185149,"description":"","headers":[],"isPrivate":false,"metaSortKey":-1571445185149,"method":"GET","modified":1571445208982,"name":"Index","parameters":[],"parentId":"fld_7ffd25012c4243dfb1dc9621e5932cc6","settingDisableRenderRequestBody":false,"settingEncodeUrl":true,"settingRebuildPath":true,"settingSendCookies":true,"settingStoreCookies":true,"url":"{{ base_url  }}/customers","_type":"request"},{"_id":"req_a53e99e65203416aa9bcd223f8892d99","authentication":{"token":"{{ token  }}","type":"bearer"},"body":{"mimeType":"application/json","text":"{\n\t\"name\": \"Livia 1\",\n  \"lastName\": \"Nishino\",\n  \"email\": \"livia2@gmail.com\",\n  \"phone\": \"61982816409\"\n}\n\n"},"created":1571303986226,"description":"","headers":[{"id":"pair_a3e2297aa0fd42afb0b628b3d79b714f","name":"Content-Type","value":"application/json"}],"isPrivate":false,"metaSortKey":-1571303986226,"method":"POST","modified":1571443716005,"name":"Create","parameters":[],"parentId":"fld_7ffd25012c4243dfb1dc9621e5932cc6","settingDisableRenderRequestBody":false,"settingEncodeUrl":true,"settingRebuildPath":true,"settingSendCookies":true,"settingStoreCookies":true,"url":"{{ base_url  }}/customers","_type":"request"},{"_id":"req_07de1a287795413e97b9b2ac2e0ee6d8","authentication":{},"body":{"mimeType":"application/json","text":"{\n\t\"email\": \"gilmar.basilio@gmail.com\",\n\t\"password\": \"abc1234567\"\n}"},"created":1570964419255,"description":"","headers":[{"id":"pair_15bf16c2c7a7465aa9f98c8b37f053fa","name":"Content-Type","value":"application/json"}],"isPrivate":false,"metaSortKey":-1570964419255,"method":"POST","modified":1572909613834,"name":"Create","parameters":[],"parentId":"fld_33a0c9eb84bc4949ae943287aba96eaf","settingDisableRenderRequestBody":false,"settingEncodeUrl":true,"settingRebuildPath":true,"settingSendCookies":true,"settingStoreCookies":true,"url":"{{ base_url  }}/sessions","_type":"request"},{"_id":"fld_33a0c9eb84bc4949ae943287aba96eaf","created":1570964408028,"description":"","environment":{},"environmentPropertyOrder":null,"metaSortKey":-1570964408028,"modified":1572780323655,"name":"Sessions","parentId":"wrk_f49c733311f24289aaa06736ec4c7ef9","_type":"request_group"},{"_id":"req_147e2a830e234defa0b3376810e3c156","authentication":{},"body":{"mimeType":"application/json","text":"{\n\t\"username\": \"Gilmar Basilio\",\n\t\"email\": \"gilmar.basilio@gmail.com\",\n\t\"password\": \"abc123456\"\n}"},"created":1570961311169,"description":"","headers":[{"id":"pair_de19700748a14e02a1f324e9ff23e9b8","name":"Content-Type","value":"application/json"}],"isPrivate":false,"metaSortKey":-1570961311169,"method":"POST","modified":1572780424654,"name":"Create","parameters":[],"parentId":"fld_b88be470dc1d43c6aad2e2d8a5a9d60a","settingDisableRenderRequestBody":false,"settingEncodeUrl":true,"settingRebuildPath":true,"settingSendCookies":true,"settingStoreCookies":true,"url":"{{ base_url  }}/users","_type":"request"},{"_id":"fld_b88be470dc1d43c6aad2e2d8a5a9d60a","created":1570961305406,"description":"","environment":{},"environmentPropertyOrder":null,"metaSortKey":-1570961305406,"modified":1572779785272,"name":"Users","parentId":"wrk_f49c733311f24289aaa06736ec4c7ef9","_type":"request_group"},{"_id":"env_c223e844e3470d1fd4337e38133d5234233b1933","color":null,"created":1570960543861,"data":{"base_url":"http://localhost:3333","token":"eyJhbGciOiJIUzI1NiIsInR5cCI6IkpXVCJ9.eyJ1c2VySWQiOjIsImVtYWlsIjoiZ2lsbWFyLmJhc2lsaW9AZ21haWwuY29tIiwiaWF0IjoxNTcxOTA3ODY0LCJleHAiOjE1NzE5OTQyNjR9.AWP3to5Azb95Jl-_dWL7oZvreNJbifywgyiNbGfPuWE"},"dataPropertyOrder":{"&":["base_url","token"]},"isPrivate":false,"metaSortKey":1570960543862,"modified":1571907881053,"name":"Base Environment","parentId":"wrk_f49c733311f24289aaa06736ec4c7ef9","_type":"environment"},{"_id":"jar_c223e844e3470d1fd4337e38133d5234233b1933","cookies":[],"created":1570960543867,"modified":1570960543867,"name":"Default Jar","parentId":"wrk_f49c733311f24289aaa06736ec4c7ef9","_type":"cookie_jar"}]}